odoo/addons/mail_show_follower/README.rst
odoo/addons/mail_show_follower/__init__.py
odoo/addons/mail_show_follower/__manifest__.py
odoo/addons/mail_show_follower/data/config_parameter_data.xml
odoo/addons/mail_show_follower/i18n/ca.po
odoo/addons/mail_show_follower/i18n/es.po
odoo/addons/mail_show_follower/i18n/fr.po
odoo/addons/mail_show_follower/i18n/it.po
odoo/addons/mail_show_follower/i18n/mail_show_follower.pot
odoo/addons/mail_show_follower/i18n/pt_BR.po
odoo/addons/mail_show_follower/models/__init__.py
odoo/addons/mail_show_follower/models/mail_mail.py
odoo/addons/mail_show_follower/models/res_company.py
odoo/addons/mail_show_follower/models/res_config_settings.py
odoo/addons/mail_show_follower/models/res_partner.py
odoo/addons/mail_show_follower/models/res_users.py
odoo/addons/mail_show_follower/readme/CONFIGURE.md
odoo/addons/mail_show_follower/readme/CONTRIBUTORS.md
odoo/addons/mail_show_follower/readme/DESCRIPTION.md
odoo/addons/mail_show_follower/readme/USAGE.md
odoo/addons/mail_show_follower/static/description/icon.png
odoo/addons/mail_show_follower/static/description/index.html
odoo/addons/mail_show_follower/views/res_config_settings.xml
odoo/addons/mail_show_follower/views/res_users.xml
odoo_addon_mail_show_follower-18.0.1.0.2.dist-info/METADATA
odoo_addon_mail_show_follower-18.0.1.0.2.dist-info/WHEEL
odoo_addon_mail_show_follower-18.0.1.0.2.dist-info/top_level.txt
odoo_addon_mail_show_follower-18.0.1.0.2.dist-info/RECORD
